atri_react/Accordion.py
atri_react/Alert.py
atri_react/Anchor.py
atri_react/AreaChart.py
atri_react/Badge.py
atri_react/BarChart.py
atri_react/Breadcrumb.py
atri_react/Button.py
atri_react/CandleStick.py
atri_react/Card.py
atri_react/Carousel.py
atri_react/Cascader.py
atri_react/Checkbox.py
atri_react/CodeMirror.py
atri_react/Countdown.py
atri_react/Countup.py
atri_react/DatePicker.py
atri_react/Div.py
atri_react/Drawer.py
atri_react/Dropdown.py
atri_react/Flex.py
atri_react/Form.py
atri_react/GanttChart.py
atri_react/HistogramChart.py
atri_react/Icon.py
atri_react/Iframe.py
atri_react/Image.py
atri_react/Input.py
atri_react/InputNumber.py
atri_react/LineChart.py
atri_react/Link.py
atri_react/Menu.py
atri_react/Modal.py
atri_react/Overlay.py
atri_react/PieChart.py
atri_react/Radio.py
atri_react/Rating.py
atri_react/Repeating.py
atri_react/ScatterChart.py
atri_react/Search.py
atri_react/Select.py
atri_react/Slider.py
atri_react/Statistic.py
atri_react/Step.py
atri_react/Table.py
atri_react/Tabs.py
atri_react/Tag.py
atri_react/Testimonial.py
atri_react/TextBox.py
atri_react/Textarea.py
atri_react/TimePicker.py
atri_react/Timeline.py
atri_react/TinyMCE.py
atri_react/Toggle.py
atri_react/Tree.py
atri_react/TreemapChart.py
atri_react/UnorderedList.py
atri_react/Upload.py
atri_react/VerticalMenu.py
atri_react/Video.py
atri_react/__init__.py
config/__init__.py
config/package.json
atri_react-1.0.0a26.dist-info/METADATA
atri_react-1.0.0a26.dist-info/WHEEL
atri_react-1.0.0a26.dist-info/top_level.txt
atri_react-1.0.0a26.dist-info/RECORD
