Metadata-Version: 2.1
Name: atri-react
Version: 1.0.0a26
Summary: > TODO: description
Home-page: https://github.com/cruxcode/atrilabs-engine#readme
Author: cruxcode
Author-email: swaroopshyam0@gmail.com
License: GPLv3
Project-URL: Source, https://github.com/cruxcode/atrilabs-engine.git
Requires-Python: >=3.7
Requires-Dist: atri-core
